{"FPS_enabled":true,"PERSPECTIVEMOD_enabled":true,"Perspective Mod_x":200,"PERSPECTIVEMOD_y":100,"Cords_enabled":true,"FPS_x":1,"FPS_y":1,"Keystrokes_enabled":true,"Cords_y":39,"Velocity_enabled":true,"Perspective Mod_y":100,"Cords_x":0,"Keystrokes_y":209,"PerspectiveMod_enabled":false,"Keystrokes_x":419,"Ping_enabled":true,"ArmorStatus_enabled":true,"ServerName_x":1,"Time_enabled":true,"CPS_y":9,"CPS_enabled":true,"PerspectiveMod_x":200,"Velocity_x":1,"ServerName_y":18,"Velocity_y":95,"Direction_enabled":true,"PotionStatus_x":407,"Version_y":62,"PotionStatus_y":21,"PotionStatus_enabled":true,"Version_x":0,"PerspectiveMod_y":100,"Custom Enchant Glint_y":100,"CPS_x":0,"Custom Enchant Glint_x":100,"ArmorStatus_y":114,"ArmorStatus_x":-3,"Perspective Mod_enabled":true,"Ping_y":18,"Version_enabled":true,"Ping_x":0,"Time_y":85,"Time_x":0,"Direction_y":76,"Direction_x":0,"PERSPECTIVEMOD_x":200,"ServerName_enabled":true,"Custom Enchant Glint_enabled":false}